{
    "key": "group_5c29d7c874998",
    "title": "Options : Page liste événements",
    "fields": [
        {
            "key": "field_5c29d7f4689ab",
            "label": "Chapeau",
            "name": "params_archive_events_chapeau",
            "type": "textarea",
            "instructions": "",
            "required": 0,
            "conditional_logic": 0,
            "wrapper": {
                "width": "",
                "class": "",
                "id": ""
            },
            "default_value": "",
            "placeholder": "",
            "maxlength": "",
            "rows": "",
            "new_lines": ""
        }
    ],
    "location": [
        [
            {
                "param": "options_page",
                "operator": "==",
                "value": "acf-options-parametres"
            }
        ]
    ],
    "menu_order": 5,
    "position": "normal",
    "style": "default",
    "label_placement": "top",
    "instruction_placement": "label",
    "hide_on_screen": "",
    "active": 1,
    "description": "",
    "modified": 1548026071
}